Metadata-Version: 2.1
Name: custom-output
Version: 0.0.2
Summary: UNKNOWN
Home-page: https://github.com/thomassoni/custom_output
Author: thomassoni
Author-email: thomassoniofc@gmail.com
License: UNKNOWN
Project-URL: Código fonte, https://github.com/thomassoni/custom_output
Project-URL: tracker, https://github.com/thomassoni/custom_output/issues
Platform: UNKNOWN
